setup.py
omnisync/__init__.py
omnisync/configuration.py
omnisync/fileobject.py
omnisync/main.py
omnisync/progress.py
omnisync/transportmount.py
omnisync/unit_tests.py
omnisync/urlfunctions.py
omnisync/version.py
omnisync.egg-info/PKG-INFO
omnisync.egg-info/SOURCES.txt
omnisync.egg-info/dependency_links.txt
omnisync.egg-info/entry_points.txt
omnisync.egg-info/top_level.txt
omnisync/transports/__init__.py
omnisync/transports/file.py
omnisync/transports/s3.py
omnisync/transports/sftp.py
omnisync/transports/virtual.py