Metadata-Version: 1.1
Name: omnisync
Version: 0.1a2
Summary: Multiprotocol file synchroniser.
Home-page: http://launchpad.net/omnisync/
Author: Stavros Korokithakis
Author-email: stavros@korokithakis.net
License: Simplified BSD License
Platform: UNKNOWN
Requires: paramiko
Requires: boto
